jitsi_py/__init__.py
jitsi_py/version.py
jitsi_py/api/__init__.py
jitsi_py/api/rest.py
jitsi_py/api/websocket.py
jitsi_py/core/__init__.py
jitsi_py/core/client.py
jitsi_py/core/room.py
jitsi_py/features/__init__.py
jitsi_py/features/audio.py
jitsi_py/features/recording.py
jitsi_py/features/streaming.py
jitsi_py/features/video.py
jitsi_py/integrations/__init__.py
jitsi_py/integrations/django.py
jitsi_py/security/__init__.py
jitsi_py/security/tokens.py
jitsi_py/utils/__init__.py
jitsi_py/utils/cli.py
jitsi_py/utils/config.py
jitsi_py/utils/url.py
tests/__init__.py
tests/conftest.py
tests/e2e/__init__.py
tests/e2e/setup_test_env.py
tests/e2e/test_room_creation.py
tests/integration/__init__.py
tests/integration/test_recording.py
tests/integration/test_rest_api.py
tests/integration/test_websocket.py
tests/mocks/__init__.py
tests/mocks/rest_responses.py
tests/mocks/websocket_events.py
tests/performance/test_room_creation_performance.py
tests/security/test_token_security.py
tests/unit/__init__.py
tests/unit/test_client.py
tests/unit/test_tokens.py
tests/unit/test_url_builder.py
jitsi_py-2.1.0.dist-info/METADATA
jitsi_py-2.1.0.dist-info/WHEEL
jitsi_py-2.1.0.dist-info/entry_points.txt
jitsi_py-2.1.0.dist-info/top_level.txt
jitsi_py-2.1.0.dist-info/RECORD
