Metadata-Version: 2.4
Name: jitsi-py
Version: 2.1.0
Summary: Python integration for Jitsi Meet video conferencing
Home-page: https://github.com/Kabhishek18/jitsi-plugin
Author: Kumar Abhishek
Author-email: developer@kabhishek18.com
Project-URL: Documentation, https://github.com/Kabhishek18/jitsi-plugin/docs
Project-URL: Source, https://github.com/Kabhishek18/jitsi-plugin
Project-URL: Tracker, https://github.com/Kabhishek18/jitsi-plugin/issues
Keywords: jitsi,video conference,webrtc,meetings,video chat,real-time communication
Classifier: Development Status :: 3 - Alpha
Classifier: Intended Audience :: Developers
Classifier: License :: OSI Approved :: MIT License
Classifier: Programming Language :: Python :: 3
Classifier: Programming Language :: Python :: 3.8
Classifier: Programming Language :: Python :: 3.9
Classifier: Programming Language :: Python :: 3.10
Classifier: Programming Language :: Python :: 3.11
Classifier: Topic :: Communications :: Conferencing
Classifier: Topic :: Multimedia :: Video
Classifier: Topic :: Software Development :: Libraries :: Python Modules
Classifier: Operating System :: OS Independent
Classifier: Framework :: Django
Classifier: Framework :: Flask
Classifier: Framework :: FastAPI
Requires-Python: >=3.8
Requires-Dist: requests>=2.25.0
Requires-Dist: pyjwt>=2.0.0
Requires-Dist: websocket-client>=1.0.0
Requires-Dist: pyyaml>=5.1.0
Provides-Extra: django
Requires-Dist: django>=3.0.0; extra == "django"
Provides-Extra: flask
Requires-Dist: flask>=2.0.0; extra == "flask"
Provides-Extra: fastapi
Requires-Dist: fastapi>=0.70.0; extra == "fastapi"
Requires-Dist: uvicorn>=0.15.0; extra == "fastapi"
Provides-Extra: aws
Requires-Dist: boto3>=1.17.0; extra == "aws"
Provides-Extra: ai
Requires-Dist: openai>=0.27.0; extra == "ai"
Requires-Dist: whisper>=1.0.0; extra == "ai"
Provides-Extra: dev
Requires-Dist: pytest>=6.0.0; extra == "dev"
Requires-Dist: pytest-cov>=2.12.0; extra == "dev"
Requires-Dist: pytest-mock>=3.6.0; extra == "dev"
Requires-Dist: requests-mock>=1.9.0; extra == "dev"
Requires-Dist: black>=21.5b2; extra == "dev"
Requires-Dist: flake8>=3.9.0; extra == "dev"
Requires-Dist: mypy>=0.812; extra == "dev"
Provides-Extra: docs
Requires-Dist: sphinx>=4.0.0; extra == "docs"
Requires-Dist: sphinx-rtd-theme>=0.5.0; extra == "docs"
Requires-Dist: sphinx-autoapi>=1.8.0; extra == "docs"
Provides-Extra: all
Requires-Dist: django>=3.0.0; extra == "all"
Requires-Dist: flask>=2.0.0; extra == "all"
Requires-Dist: fastapi>=0.70.0; extra == "all"
Requires-Dist: uvicorn>=0.15.0; extra == "all"
Requires-Dist: boto3>=1.17.0; extra == "all"
Requires-Dist: openai>=0.27.0; extra == "all"
Requires-Dist: whisper>=1.0.0; extra == "all"
Dynamic: author
Dynamic: author-email
Dynamic: classifier
Dynamic: description
Dynamic: description-content-type
Dynamic: home-page
Dynamic: keywords
Dynamic: project-url
Dynamic: provides-extra
Dynamic: requires-dist
Dynamic: requires-python
Dynamic: summary
